Workbook
Name Aporte: Investimentos!$D$18
Name Patrimonio: Investimentos!$D$21
Name Qtd_Anos: Investimentos!$D$19
Name Rendimento_Carteira: Investimentos!$D$14
Name Rendimento_de_Carteira: Investimentos!$D$14
Name Rendomento_de_Carteira: Investimentos!$D$14
Name Salario: Investimentos!$D$13
Name Salário: Investimentos!$D$13
Name Sugestao_Investimento: Investimentos!$D$15
Name Sugestão_Investimento: Investimentos!$D$15
Name Taxa_mensal: Investimentos!$D$20

Sheet Investimentos
B12: CONFIGURAÇÕES
B13: Salário | D13: 5250
B14: Rendimento Carteira | D14: 0.01
B15: Sugestão de Investimento 30% | D15: =D13*30% -> 1575
B17: Investimento Mensal
B18: Quanto investir por mês? | D18: 950
B19: Por quantos anos? | D19: 5
B20: Taxa de Rendimento mensal? | D20: 0.01079
B21: Patrimônio acumulado? | D21: =FV(Taxa_mensal,Qtd_Anos*12,Aporte*-1) -> 79588.068
B22: Dividendos Mensais? | D22: =Patrimonio*$D$14 -> 795.88068
B24: Cenários | D24: Dividendo
A25: 2 | B25: Quanto em 2 anos? | C25: =FV($D$20,$A25*12,$D$18*-1) -> 25866.246 | D25: =C25*Rendimento_Carteira -> 258.66246
A26: 5 | B26: Quanto em 5 anos? | C26: =FV($D$20,$A26*12,$D$18*-1) -> 79588.068 | D26: =C26*Rendimento_Carteira -> 795.88068
A27: 10 | B27: Quanto em 10 anos? | C27: =FV($D$20,$A27*12,$D$18*-1) -> 231120 | D27: =C27*Rendimento_Carteira -> 2311.2
A28: 20 | B28: Quanto em 20 anos? | C28: =FV($D$20,$A28*12,$D$18*-1) -> 1068938.5 | D28: =C28*Rendimento_Carteira -> 10689.385
A29: 30 | B29: Quanto em 30 anos? | C29: =FV($D$20,$A29*12,$D$18*-1) -> 4106061.2 | D29: =C29*Rendimento_Carteira -> 41060.612
B32: PERFIL | C32: Moderado
B33: Valor Investido por Mês | C33: =Aporte -> 950
B35: TIPO DE FII | C35: PERCENTUAL SUGERIDO | D35: VALORES
B36: PAPEL | C36: =VLOOKUP($C$32&"-"&B36,'Planilha de Apoio'!$A$4:$D$21,4,FALSE) -> 0.32 | D36: =C36*$C$33 -> 304
B37: TIJOLO | C37: =VLOOKUP($C$32&"-"&B37,'Planilha de Apoio'!$A$4:$D$21,4,FALSE) -> 0.3 | D37: =C37*$C$33 -> 285
B38: HIBRIDO | C38: =VLOOKUP($C$32&"-"&B38,'Planilha de Apoio'!$A$4:$D$21,4,FALSE) -> 0.08 | D38: =C38*$C$33 -> 76
B39: FOFs | C39: =VLOOKUP($C$32&"-"&B39,'Planilha de Apoio'!$A$4:$D$21,4,FALSE) -> 0.1 | D39: =C39*$C$33 -> 95
B40: DESENVOLVIMENTO | C40: =VLOOKUP($C$32&"-"&B40,'Planilha de Apoio'!$A$4:$D$21,4,FALSE) -> 0.1 | D40: =C40*$C$33 -> 95
B41: HOTELARIA | C41: =VLOOKUP($C$32&"-"&B41,'Planilha de Apoio'!$A$4:$D$21,4,FALSE) -> 0.1 | D41: =C41*$C$33 -> 95
D42: =SUM(D36:D41) -> 950

Sheet Planilha de Apoio
J2: %
A3: CHAVE | B3: PERFIL | C3: TIPO DE FII | D3: PERCENTUAL | H3: Moderado-TIJOLO | J3: =VLOOKUP(H3,$A$1:$D$22,4,FALSE) -> 0.3
A4: Conservador-PAPEL | B4: Conservador | C4: PAPEL | D4: 0.3
A5: Conservador-TIJOLO | B5: Conservador | C5: TIJOLO | D5: 0.5
A6: Conservador-HIBRIDO | B6: Conservador | C6: HIBRIDO | D6: 0.1
A7: Conservador-FOFs | B7: Conservador | C7: FOFs | D7: 0.1
A8: Conservador-DESENVOLVIMENTO | B8: Conservador | C8: DESENVOLVIMENTO | D8: 0
A9: Conservador-HOTELARIA | B9: Conservador | C9: HOTELARIA | D9: 0
A10: Moderado-PAPEL | B10: Moderado | C10: PAPEL | D10: 0.32
A11: Moderado-TIJOLO | B11: Moderado | C11: TIJOLO | D11: 0.3
A12: Moderado-HIBRIDO | B12: Moderado | C12: HIBRIDO | D12: 0.08
A13: Moderado-FOFs | B13: Moderado | C13: FOFs | D13: 0.1
A14: Moderado-DESENVOLVIMENTO | B14: Moderado | C14: DESENVOLVIMENTO | D14: 0.1
A15: Moderado-HOTELARIA | B15: Moderado | C15: HOTELARIA | D15: 0.1
... A21: Agressivo-HOTELARIA | B21: Agressivo | C21: HOTELARIA | D21: 0.1
